defisdk/__init__.py
defisdk/constants.py
defisdk/entities.py
defisdk/enums.py
defisdk/errors.py
defisdk/serializers.py
defisdk/settings.py
defisdk/utils.py
defisdk/version.py
defisdk/abis/__init__.py
defisdk/abis/router.py
defisdk/repositories/__init__.py
defisdk/repositories/base.py
defisdk/repositories/defi.py
defisdk/repositories/ethereum.py
tests/__init__.py
defisdk-0.0.7.dist-info/METADATA
defisdk-0.0.7.dist-info/WHEEL
defisdk-0.0.7.dist-info/top_level.txt
defisdk-0.0.7.dist-info/RECORD
