Metadata-Version: 2.1
Name: defisdk
Version: 0.0.7
Summary: DeFiSDK.py
Home-page: https://github.com/zeriontech/defi-sdk-py
Author: Alex Bash
Author-email: alexey@zerion.io
License: UNKNOWN
Platform: UNKNOWN
Requires-Python: >=3.7
Requires-Dist: aiohttp (==3.7.4.post0)
Requires-Dist: furl (==2.1.3)
Requires-Dist: pysha3 (==1.0.2)
